{"is_source_file": true, "format": "Java", "description": "Defines a JPA entity class 'Note' representing a note with fields for title, content, and audit timestamps, including lifecycle hooks for timestamp management.", "external_files": ["jakarta.persistence.*", "java.time.OffsetDateTime"], "external_methods": ["jakarta.persistence.*.GeneratedValue", "jakarta.persistence.*.Id", "jakarta.persistence.*.Column", "jakarta.persistence.*.Lob", "jakarta.persistence.*.PrePersist", "jakarta.persistence.*.PreUpdate", "java.time.OffsetDateTime.now"], "published": ["com.example.notesappbackend.entity.Note"], "classes": [{"name": "Note", "description": "JPA entity representing a note with id, title, content, createdAt, and updatedAt fields, including lifecycle methods for setting timestamps."}], "methods": [{"name": "Note()", "description": "Default constructor."}, {"name": "Note(String title, String content)", "description": "Constructor to initialize a note with title and content."}, {"name": "onCreate()", "description": "Lifecycle callback method to set createdAt and updatedAt timestamps before persisting."}, {"name": "onUpdate()", "description": "Lifecycle callback method to update the updatedAt timestamp before updating."}, {"name": "getId()", "description": "Returns the note's id."}, {"name": "setId(Long id)", "description": "Sets the note's id."}, {"name": "getTitle()", "description": "Returns the note's title."}, {"name": "setTitle(String title)", "description": "Sets the note's title."}, {"name": "getContent()", "description": "Returns the note's content."}, {"name": "setContent(String content)", "description": "Sets the note's content."}, {"name": "getCreatedAt()", "description": "Returns the creation timestamp."}, {"name": "setCreatedAt(OffsetDateTime createdAt)", "description": "Sets the creation timestamp."}, {"name": "getUpdatedAt()", "description": "Returns the last updated timestamp."}, {"name": "setUpdatedAt(OffsetDateTime updatedAt)", "description": "Sets the last updated timestamp."}], "calls": ["OffsetDateTime.now()"], "search-terms": ["Note entity", "JPA entity", "Auditing timestamps", "Note class", "Note.java", "entity mapping"], "state": 2, "file_id": 6, "knowledge_revision": 13, "git_revision": "", "hash": "69861ba3414b38b217007ef056bb5aae", "format-version": 4, "code-base-name": "notes_app_backend", "filename": "notes_app_backend/src/main/java/com/example/notesappbackend/entity/Note.java", "revision_history": [{"13": ""}]}