{"is_source_file": true, "format": "Java", "description": "This Java configuration class defines OpenAPI metadata for a Spring Boot application, setting up API info, tags, contact info, license, and external documentation for API documentation purposes.", "external_files": [], "external_methods": [], "published": ["notesOpenAPI"], "classes": [{"name": "OpenApiConfig", "description": "Configuration class that creates an OpenAPI bean to provide API documentation metadata for the Notes App backend."}], "methods": [{"name": "notesOpenAPI", "description": "Bean method that constructs and returns an OpenAPI object with application-specific info, tags, contact, license, and external documentation."}], "calls": ["new OpenAPI()", "new Info()", "new Contact()", "new License()", "new Tag()", "new ExternalDocumentation()"], "search-terms": ["OpenAPI", "API documentation", "Spring Boot configuration", "OpenApiConfig", "api info setup", "API tags", "external documentation"], "state": 2, "file_id": 16, "knowledge_revision": 36, "git_revision": "", "hash": "34f05ae16d6a5c714ecb4cc063f714eb", "format-version": 4, "code-base-name": "notes_app_backend", "filename": "notes_app_backend/src/main/java/com/example/notesappbackend/config/OpenApiConfig.java", "revision_history": [{"36": ""}]}